[
{
    "domain": ".x.com",
    "expirationDate": 1756386915.606884,
    "hostOnly": false,
    "httpOnly": true,
    "name": "__cf_bm",
    "path": "/",
    "sameSite": "lax",
    "secure": true,
    "session": false,
    "storeId": "0",
    "value": "kBO9KP9ez5woSG7LOkYCGoyyzgL52N.p7ICfIOdVMnU-1756385115-1.0.1.1-yE1crDO1WYuGJumz7LWevWgPbqtro8qijLan6x8_8rs4XjjNSsOe9tVUujq_LMkazVgRckyzp6G13De21IpGXkfnW6TmEKFMN0YnB2JKyiw",
    "id": 1
},
{
    "domain": ".x.com",
    "expirationDate": 1790945144,
    "hostOnly": false,
    "httpOnly": false,
    "name": "__cuid",
    "path": "/",
    "sameSite": "lax",
    "secure": false,
    "session": false,
    "storeId": "0",
    "value": "95a1a11064634e229acbc5611a89df81",
    "id": 2
},
{
    "domain": ".x.com",
    "expirationDate": 1756471544.081727,
    "hostOnly": false,
    "httpOnly": true,
    "name": "att",
    "path": "/",
    "sameSite": "lax",
    "secure": true,
    "session": false,
    "storeId": "0",
    "value": "1-04hXXqidG4Lher1mUBlOZmuT1N8GAxVtQzRgW03R",
    "id": 3
},
{
    "domain": ".x.com",
    "expirationDate": 1790599543.581665,
    "hostOnly": false,
    "httpOnly": true,
    "name": "auth_token",
    "path": "/",
    "sameSite": "lax",
    "secure": true,
    "session": false,
    "storeId": "0",
    "value": "c9dd70deb626594154fdc7557c8b6027e5170a4e",
    "id": 4
},
{
    "domain": ".x.com",
    "expirationDate": 1790599543.869489,
    "hostOnly": false,
    "httpOnly": false,
    "name": "ct0",
    "path": "/",
    "sameSite": "lax",
    "secure": true,
    "session": false,
    "storeId": "0",
    "value": "df5d7f93125e64c58813bd766fd7e91b35cad6978bb20d79fea31420e36b401d93c215921211c7f5b431ac7475774a132f0ad7f49271d7edc131faf15f6ef3fd9ff312765a8034404c562f056df40c4f",
    "id": 5
},
{
    "domain": ".x.com",
    "expirationDate": 1771937146.735384,
    "hostOnly": false,
    "httpOnly": false,
    "name": "d_prefs",
    "path": "/",
    "sameSite": "lax",
    "secure": true,
    "session": false,
    "storeId": "0",
    "value": "MToxLGNvbnNlbnRfdmVyc2lvbjoyLHRleHRfdmVyc2lvbjoxMDAw",
    "id": 6
},
{
    "domain": ".x.com",
    "expirationDate": 1756394115.668331,
    "hostOnly": false,
    "httpOnly": false,
    "name": "gt",
    "path": "/",
    "sameSite": "lax",
    "secure": true,
    "session": false,
    "storeId": "0",
    "value": "1961047424291553669",
    "id": 7
},
{
    "domain": ".x.com",
    "expirationDate": 1790599515.60678,
    "hostOnly": false,
    "httpOnly": false,
    "name": "guest_id",
    "path": "/",
    "sameSite": "lax",
    "secure": true,
    "session": false,
    "storeId": "0",
    "value": "v1%3A175638511508269479",
    "id": 8
},
{
    "domain": ".x.com",
    "expirationDate": 1790599546.978116,
    "hostOnly": false,
    "httpOnly": false,
    "name": "guest_id_ads",
    "path": "/",
    "sameSite": "lax",
    "secure": true,
    "session": false,
    "storeId": "0",
    "value": "v1%3A175638511508269479",
    "id": 9
},
{
    "domain": ".x.com",
    "expirationDate": 1790599546.978238,
    "hostOnly": false,
    "httpOnly": false,
    "name": "guest_id_marketing",
    "path": "/",
    "sameSite": "lax",
    "secure": true,
    "session": false,
    "storeId": "0",
    "value": "v1%3A175638511508269479",
    "id": 10
},
{
    "domain": ".x.com",
    "expirationDate": 1790599543.581459,
    "hostOnly": false,
    "httpOnly": true,
    "name": "kdt",
    "path": "/",
    "sameSite": "lax",
    "secure": true,
    "session": false,
    "storeId": "0",
    "value": "NOOk1mfSbrbTJS4YRs6VZ0By6e8QDdw8Lj6gSsTk",
    "id": 11
},
{
    "domain": ".x.com",
    "expirationDate": 1790599546.9783,
    "hostOnly": false,
    "httpOnly": false,
    "name": "personalization_id",
    "path": "/",
    "sameSite": "lax",
    "secure": true,
    "session": false,
    "storeId": "0",
    "value": "\"v1_u2GpuKrfW/kdrkoI+6/4UQ==\"",
    "id": 12
},
{
    "domain": ".x.com",
    "expirationDate": 1787921223.348743,
    "hostOnly": false,
    "httpOnly": false,
    "name": "twid",
    "path": "/",
    "sameSite": "lax",
    "secure": true,
    "session": false,
    "storeId": "0",
    "value": "u%3D1959555942212673536",
    "id": 13
},
{
    "domain": "x.com",
    "hostOnly": true,
    "httpOnly": false,
    "name": "lang",
    "path": "/",
    "sameSite": "lax",
    "secure": false,
    "session": true,
    "storeId": "0",
    "value": "en",
    "id": 14
}
]
